setup.py
favourite_distributions/Binomialdistribution.py
favourite_distributions/Gaussiandistribution.py
favourite_distributions/Generaldistribution.py
favourite_distributions/__init__.py
favourite_distributions.egg-info/PKG-INFO
favourite_distributions.egg-info/SOURCES.txt
favourite_distributions.egg-info/dependency_links.txt
favourite_distributions.egg-info/not-zip-safe
favourite_distributions.egg-info/top_level.txt