Metadata-Version: 1.0
Name: favourite-distributions
Version: 0.1
Summary: Gaussian distributions
Home-page: UNKNOWN
Author: Stefan Decker
Author-email: sba.decker@gmail.com
License: UNKNOWN
Platform: UNKNOWN
